{
    "questions": [
        {
            "question": "冷水的内能为0",
            "answer": "F",
            "difficuly": 1,
            "part": "尚未完成的功能"
        },
        {
            "question": "反射角等于入射角",
            "answer": "T",
            "difficuly": 2,
            "part": "尚未完成的功能"
        },
        {
            "question": "机械效率不可能为100%",
            "answer": "T",
            "difficuly": 1,
            "part": "尚未完成的功能"
        },
        {
            "question": "电动机的工作原理是通电导线在磁场中会受到力的作用",
            "answer": "T",
            "difficuly": 1,
            "part": "尚未完成的功能"
        },
        {
            "question": "磁感线的方向是从S极出发回到N极",
            "answer": "F",
            "difficuly": 0,
            "part": "尚未完成的功能"
        },
        {
            "question": "指南针的N极指向地磁南极",
            "answer": "T",
            "difficuly": 0,
            "part": "尚未完成的功能"
        },
        {
            "question": "地磁南北极与地理南北极完全重合",
            "answer": "F",
            "difficuly": 0,
            "part": "尚未完成的功能"
        },
        {
            "question": "电路中有电流，一定有电压",
            "answer": "T",
            "difficuly": 2,
            "part": "尚未完成的功能"
        },
        {
            "question": "电路中有电压，一定有电流",
            "answer": "F",
            "difficuly": 2,
            "part": "尚未完成的功能"
        },
        {
            "question": "物体的内能增加，温度一定改变",
            "answer": "F",
            "difficuly": 2,
            "part": "尚未完成的功能"
        },
        {
            "question": "物体的温度不变，内能一定不变",
            "answer": "F",
            "difficuly": 2,
            "part": "尚未完成的功能"
        },
        {
            "question": "Q=cmΔt",
            "answer": "T",
            "difficuly": 0,
            "part": "尚未完成的功能"
        },
        {
            "question": "W=Pt",
            "answer": "T",
            "difficuly": 0,
            "part": "尚未完成的功能"
        },
        {
            "question": "小明推一个大箱子，没推动，因为大箱子受到的摩擦力大于受到的推力",
            "answer": "F",
            "difficuly": 2,
            "part": "尚未完成的功能"
        },
        {
            "question": "水是常见物质中比热容最大的",
            "answer": "T",
            "difficuly": 1,
            "part": "尚未完成的功能"
        },
        {
            "question": "物体受平衡力时，保持静止或做匀速直线运动",
            "answer": "T",
            "difficuly": 1,
            "part": "尚未完成的功能"
        },
        {
            "question": "使用测电笔时，不能接触后边的金属",
            "answer": "F",
            "difficuly": 1,
            "part": "尚未完成的功能"
        },
        {
            "question": "热机效率可能为100%",
            "answer": "F",
            "difficuly": 1,
            "part": "尚未完成的功能"
        },
        {
            "question": "物体温度升高，内能一定增大",
            "answer": "T",
            "difficuly": 3,
            "part": "尚未完成的功能"
        },
        {
            "question": "一瓶运动饮料所具有的热量为3KJ",
            "answer": "F",
            "difficuly": 2,
            "part": "尚未完成的功能"
        },
        {
            "question": "在所有常见燃料中氢的热值最大",
            "answer": "T",
            "difficuly": 1,
            "part": "尚未完成的功能"
        },
        {
            "question": "P=Wt",
            "answer": "F",
            "difficuly": 0,
            "part": "尚未完成的功能"
        },
        {
            "question": "同名磁极相互排斥，异名磁极相互吸引",
            "answer": "T",
            "difficuly": 0,
            "part": "尚未完成的功能"
        },
        {
            "question": "电流的方向与正电荷定向移动的方向相反",
            "answer": "F",
            "difficuly": 0,
            "part": "尚未完成的功能"
        },
        {
            "question": "电池外部，电子从正极流向负极",
            "answer": "F",
            "difficuly": 1,
            "part": "尚未完成的功能"
        },
        {
            "question": "银的导电性比铜好，所以应该用银制导线",
            "answer": "F",
            "difficuly": 0,
            "part": "尚未完成的功能"
        },
        {
            "question": "保险丝的熔点较低",
            "answer": "T",
            "difficuly": 1,
            "part": "尚未完成的功能"
        },
        {
            "question": "电流表大量程的分度值为0.2A",
            "answer": "F",
            "difficuly": 0,
            "part": "尚未完成的功能"
        },
        {
            "question": "电压表大量程为0~15V",
            "answer": "T",
            "difficuly": 0,
            "part": "尚未完成的功能"
        },
        {
            "question": "人体的电阻很大",
            "answer": "T",
            "difficuly": 0,
            "part": "尚未完成的功能"
        },
        {
            "question": "测电笔中用氖管是因为稀有气体通电会发光",
            "answer": "T",
            "difficuly": 0,
            "part": "尚未完成的功能"
        },
        {
            "question": "使用测电笔时，有电流通过人体入地",
            "answer": "T",
            "difficuly": 1,
            "part": "尚未完成的功能"
        },
        {
            "question": "当光源与凸透镜的距离为x<f时，不成像",
            "answer": "F",
            "difficuly": 1,
            "part": "尚未完成的功能"
        },
        {
            "question": "当光源与凸透镜的距离为f<x<2f时，像与凸透镜的距离为x>2f，且成倒立放大的实像",
            "answer": "T",
            "difficuly": 2,
            "part": "尚未完成的功能"
        },
        {
            "question": "牛顿是力的单位",
            "answer": "T",
            "difficuly": 1,
            "part": "尚未完成的功能"
        },
        {
            "question": "焦耳是功的单位",
            "answer": "T",
            "difficuly": 1,
            "part": "尚未完成的功能"
        },
        {
            "question": "W=Fs",
            "answer": "T",
            "difficuly": 0,
            "part": "尚未完成的功能"
        },
        {
            "question": "1焦=1牛·米",
            "answer": "T",
            "difficuly": 0,
            "part": "尚未完成的功能"
        },
        {
            "question": "瓦是功的单位",
            "answer": "F",
            "difficuly": 0,
            "part": "尚未完成的功能"
        },
        {
            "question": "1瓦=1焦·秒",
            "answer": "F",
            "difficuly": 0,
            "part": "尚未完成的功能"
        },
        {
            "question": "1kW·h=3.6×10的四次方J",
            "answer": "F",
            "difficuly": 0,
            "part": "尚未完成的功能"
        },
        {
            "question": "1瓦=1伏·安",
            "answer": "T",
            "difficuly": 0,
            "part": "尚未完成的功能"
        },
        {
            "question": "1Ω=1V·A",
            "answer": "F",
            "difficuly": 0,
            "part": "尚未完成的功能"
        },
        {
            "question": "测量电功率和电阻时，都可以用伏安法，实验装置也相同",
            "answer": "T",
            "difficuly": 2,
            "part": "尚未完成的功能"
        },
        {
            "question": "焦耳定律演示仪中，加热的是空气，因为空气比热容小",
            "answer": "T",
            "difficuly": 1,
            "part": "尚未完成的功能"
        },
        {
            "question": "同等质量的水和煤油，用同一热源加热相同的时间，水升温较慢，说明水的比热容小",
            "answer": "F",
            "difficuly": 1,
            "part": "尚未完成的功能"
        },
        {
            "question": "声音的传播速度为：v固体< v液体 <v气体",
            "answer": "F",
            "difficuly": 2,
            "part": "尚未完成的功能"
        },
        {
            "question": "G=mg,其中g约为9.8N/kg",
            "answer": "T",
            "difficuly": 0,
            "part": "尚未完成的功能"
        },
        {
            "question": "ρ=m/V",
            "answer": "T",
            "difficuly": 0,
            "part": "尚未完成的功能"
        },
        {
            "question": "P=ρgh",
            "answer": "T",
            "difficuly": 0,
            "part": "尚未完成的功能"
        },
        {
            "question": "当物体漂浮或悬浮时，F浮=G，因为物体处于平衡状态",
            "answer": "T",
            "difficuly": 1,
            "part": "尚未完成的功能"
        },
        {
            "question": "W=F/S",
            "answer": "F",
            "difficuly": 0,
            "part": "尚未完成的功能"
        },
        {
            "question": "η可以表示热机效率和机械效率",
            "answer": "T",
            "difficuly": 1,
            "part": "尚未完成的功能"
        },
        {
            "question": "改变内能的方式是做功和热传导",
            "answer": "F",
            "difficuly": 3,
            "part": "尚未完成的功能"
        },
        {
            "question": "热传递的三种方式：热传导，热对流，热辐射",
            "answer": "T",
            "difficuly": 3,
            "part": "尚未完成的功能"
        },
        {
            "question": "一个用丝绸摩擦过的玻璃棒靠近一个小球，若小球被吸引，则小球带负电",
            "answer": "F",
            "difficuly": 2,
            "part": "尚未完成的功能"
        },
        {
            "question": "扬声器的工作原理是通电导体在磁场中会受到力的作用",
            "answer": "T",
            "difficuly": 2,
            "part": "尚未完成的功能"
        },
        {
            "question": "电磁继电器的工作原理是通电导体在磁场中会受到力的作用",
            "answer": "F",
            "difficuly": 3,
            "part": "尚未完成的功能"
        },
        {
            "question": "用电饭煲煮饭，是将电能转化为内能",
            "answer": "T",
            "difficuly": 1,
            "part": "尚未完成的功能"
        },
        {
            "question": "多次实验的目的一定是为了减小误差",
            "answer": "F",
            "difficuly": 0,
            "part": "尚未完成的功能"
        },
        {
            "question": "物体是静止还是运动取决于所选参照物",
            "answer": "T",
            "difficuly": 1,
            "part": "尚未完成的功能"
        },
        {
            "question": "动能可能为零",
            "answer": "T",
            "difficuly": 2,
            "part": "尚未完成的功能"
        },
        {
            "question": "光在真空中传播的速度约为3.0×10的8次方km/s",
            "answer": "F",
            "difficuly": 1,
            "part": "尚未完成的功能"
        },
        {
            "question": "g=9.8N/kg 表示 1kg=9.8N",
            "answer": "F",
            "difficuly": 1,
            "part": "尚未完成的功能"
        },
        {
            "question": "水凝固后质量变小了",
            "answer": "F",
            "difficuly": 0,
            "part": "尚未完成的功能"
        },
        {
            "question": "物体的重心一定在物体上",
            "answer": "F",
            "difficuly": 0,
            "part": "尚未完成的功能"
        },
        {
            "question": "闻其声而知其人是根据音色来判断的",
            "answer": "T",
            "difficuly": 1,
            "part": "尚未完成的功能"
        },
        {
            "question": "宇航员杨利伟在“神州”五号飞船中受到的重力减小了，但他的质量保持不变",
            "answer": "T",
            "difficuly": 1,
            "part": "尚未完成的功能"
        },
        {
            "question": "噪声不是由振动产生",
            "answer": "F",
            "difficuly": 1,
            "part": "尚未完成的功能"
        },
        {
            "question": "排球在上升过程中，排球受到的重力的方向竖直向下",
            "answer": "T",
            "difficuly": 1,
            "part": "尚未完成的功能"
        },
        {
            "question": "只有相互接触的物体才会发生力的作用",
            "answer": "F",
            "difficuly": 1,
            "part": "尚未完成的功能"
        },
        {
            "question": "地面对物体的支持力与物体的重力是相互作用力",
            "answer": "F",
            "difficuly": 2,
            "part": "尚未完成的功能"
        },
        {
            "question": "鸡蛋碰石头，鸡蛋受到的力大于石头受到的力",
            "answer": "F",
            "difficuly": 2,
            "part": "尚未完成的功能"
        },
        {
            "question": "人用水平方向的力推桌子，桌子没动是因为推力小于摩擦力",
            "answer": "F",
            "difficuly": 2,
            "part": "尚未完成的功能"
        },
        {
            "question": "用船桨划水船会前行，说明力的作用是相互的",
            "answer": "T",
            "difficuly": 1,
            "part": "尚未完成的功能"
        },
        {
            "question": "小球从斜面滚下，它受到的重力的方向沿斜面向下",
            "answer": "F",
            "difficuly": 1,
            "part": "尚未完成的功能"
        },
        {
            "question": "将锤柄在石墩上撞击几下，松动的锤头就紧套在锤柄上，这是利用了锤柄的惯性",
            "answer": "F",
            "difficuly": 3,
            "part": "尚未完成的功能"
        },
        {
            "question": "踢出去的足球还能在水平地面上继续运动，是因为足球具有惯性",
            "answer": "T",
            "difficuly": 1,
            "part": "尚未完成的功能"
        },
        {
            "question": "跳远运动员助跑可以提高成绩，是利用了身体的惯性",
            "answer": "T",
            "difficuly": 1,
            "part": "尚未完成的功能"
        },
        {
            "question": "跳远时助跑是为了增大身体的惯性",
            "answer": "F",
            "difficuly": 2,
            "part": "尚未完成的功能"
        },
        {
            "question": "只有静止和做匀速运动的物体有惯性",
            "answer": "F",
            "difficuly": 1,
            "part": "尚未完成的功能"
        },
        {
            "question": "物体的惯性越大运动状态越不容易改变",
            "answer": "T",
            "difficuly": 1,
            "part": "尚未完成的功能"
        },
        {
            "question": "当物体不受力时，物体都要静止下来",
            "answer": "F",
            "difficuly": 2,
            "part": "尚未完成的功能"
        },
        {
            "question": "运动的物体不受力时，总是保持匀速直线运动",
            "answer": "T",
            "difficuly": 1,
            "part": "尚未完成的功能"
        },
        {
            "question": "踢向空中的足球，下落过程中足球运动越来越快，是因为足球受到重力的作用",
            "answer": "T",
            "difficuly": 2,
            "part": "尚未完成的功能"
        },
        {
            "question": "自由下落的苹果，受到非平衡力的作用",
            "answer": "T",
            "difficuly": 2,
            "part": "尚未完成的功能"
        },
        {
            "question": "竖直上升的排球，球在上升到最高点时速度为零，物体处于平衡状态",
            "answer": "F",
            "difficuly": 3,
            "part": "尚未完成的功能"
        },
        {
            "question": "水平地面上的足球越滚越慢说明力是维持物体运动的原因",
            "answer": "F",
            "difficuly": 1,
            "part": "尚未完成的功能"
        },
        {
            "question": "压力的方向可能沿水平方向",
            "answer": "T",
            "difficuly": 2,
            "part": "尚未完成的功能"
        },
        {
            "question": "压力越大，压强一定越大",
            "answer": "F",
            "difficuly": 0,
            "part": "尚未完成的功能"
        },
        {
            "question": "压强越大，压力的作用效果一定越明显",
            "answer": "T",
            "difficuly": 2,
            "part": "尚未完成的功能"
        },
        {
            "question": "在同种液体中，深度越大的地方压强越大",
            "answer": "T",
            "difficuly": 1,
            "part": "尚未完成的功能"
        },
        {
            "question": "在同种液体的同一深度，液体朝各个方向的压强大小一定相等",
            "answer": "T",
            "difficuly": 2,
            "part": "尚未完成的功能"
        },
        {
            "question": "容器中液体越多，液体对容器底部的压力越大",
            "answer": "F",
            "difficuly": 2,
            "part": "尚未完成的功能"
        },
        {
            "question": "马德堡半球实验第一次测量出了大气压的准确值",
            "answer": "F",
            "difficuly": 2,
            "part": "尚未完成的功能"
        },
        {
            "question": "流体流动的速度越大的位置，产生的压强越小",
            "answer": "T",
            "difficuly": 1,
            "part": "尚未完成的功能"
        },
        {
            "question": "下沉的物体不受浮力作用",
            "answer": "F",
            "difficuly": 0,
            "part": "尚未完成的功能"
        },
        {
            "question": "物体在液体中受到的浮力与液体的密度和物体水上和水下的总体积有关",
            "answer": "F",
            "difficuly": 0,
            "part": "尚未完成的功能"
        },
        {
            "question": "物体浸没在水中时，所在位置越深，受到的浮力越大",
            "answer": "F",
            "difficuly": 2,
            "part": "尚未完成的功能"
        },
        {
            "question": "一个物体受到的浮力等于它的重力，该物体一定是漂浮的",
            "answer": "F",
            "difficuly": 0,
            "part": "尚未完成的功能"
        },
        {
            "question": "作用在物体上的力越大，该力做的功一定越多",
            "answer": "F",
            "difficuly": 0,
            "part": "尚未完成的功能"
        },
        {
            "question": "铅球抛出后在空中飞行，在该过程中没有力对铅球做功",
            "answer": "F",
            "difficuly": 2,
            "part": "尚未完成的功能"
        },
        {
            "question": "排球在脱离手后上升过程中，人的推力对排球做功",
            "answer": "F",
            "difficuly": 1,
            "part": "尚未完成的功能"
        },
        {
            "question": "排球在自由下落过程中，排球所受的重力做功越来越快",
            "answer": "T",
            "difficuly": 2,
            "part": "尚未完成的功能"
        },
        {
            "question": "一个力做功越多，这个力的功率一定越大",
            "answer": "F",
            "difficuly": 0,
            "part": "尚未完成的功能"
        },
        {
            "question": "做功快的机械，其功率一定大",
            "answer": "T",
            "difficuly": 2,
            "part": "尚未完成的功能"
        },
        {
            "question": "功率越大的机械，做功时间一定越短",
            "answer": "F",
            "difficuly": 1,
            "part": "尚未完成的功能"
        },
        {
            "question": "机械所做的有用功越多，机械效率越高",
            "answer": "F",
            "difficuly": 1,
            "part": "尚未完成的功能"
        },
        {
            "question": "越省力的机械机械效率越高",
            "answer": "F",
            "difficuly": 1,
            "part": "尚未完成的功能"
        },
        {
            "question": "功率越大，机械效率越大",
            "answer": "F",
            "difficuly": 1,
            "part": "尚未完成的功能"
        },
        {
            "question": "额外功与总功的比值越大，机械效率越小",
            "answer": "T",
            "difficuly": 1,
            "part": "尚未完成的功能"
        },
        {
            "question": "使用同一个滑轮组提升物体时，物体越重机械效率越大",
            "answer": "T",
            "difficuly": 2,
            "part": "尚未完成的功能"
        },
        {
            "question": "静止的物体不能做功，不具有能",
            "answer": "F",
            "difficuly": 1,
            "part": "尚未完成的功能"
        },
        {
            "question": "速度越大的物体动能一定越大",
            "answer": "F",
            "difficuly": 1,
            "part": "尚未完成的功能"
        },
        {
            "question": "小明同学站在匀速向上运动的电梯中，他的动能增加",
            "answer": "F",
            "difficuly": 3,
            "part": "尚未完成的功能"
        },
        {
            "question": "蹦床运动员在比赛中从蹦床弹向空中的过程中，运动员的重力势能变大",
            "answer": "T",
            "difficuly": 1,
            "part": "尚未完成的功能"
        },
        {
            "question": "排球在下落过程中，排球的重力势能变小",
            "answer": "T",
            "difficuly": 1,
            "part": "尚未完成的功能"
        },
        {
            "question": "跳高运动员跳高,离开地面向上运动过程中，动能减小，势能增加",
            "answer": "T",
            "difficuly": 1,
            "part": "尚未完成的功能"
        },
        {
            "question": "滑雪运动员从山顶加速下滑的过程中，他的重力势能减少，动能增加",
            "answer": "T",
            "difficuly": 2,
            "part": "尚未完成的功能"
        },
        {
            "question": "做匀速直线运动的物体的机械能保持不变",
            "answer": "F",
            "difficuly": 1,
            "part": "尚未完成的功能"
        },
        {
            "question": "跳伞运动员从空中匀速下落过程中，他的重力势能减小，机械能不变",
            "answer": "F",
            "difficuly": 2,
            "part": "尚未完成的功能"
        },
        {
            "question": "丝绸摩擦玻璃棒，丝绸带的是正电",
            "answer": "F",
            "difficuly": 1,
            "part": "尚未完成的功能"
        },
        {
            "question": "金属导体中的电流方向与其中自由电子定向移动方向相反",
            "answer": "T",
            "difficuly": 1,
            "part": "尚未完成的功能"
        },
        {
            "question": "绝缘体不含有自由电子所以不能导电",
            "answer": "F",
            "difficuly": 1,
            "part": "尚未完成的功能"
        },
        {
            "question": "正电荷定向移动的方向是电流的方向",
            "answer": "T",
            "difficuly": 0,
            "part": "尚未完成的功能"
        },
        {
            "question": "导体的电阻是导体本身的一种性质，它的大小总是不变的",
            "answer": "F",
            "difficuly": 0,
            "part": "尚未完成的功能"
        },
        {
            "question": "电阻是导体对电流的阻碍作用，没有电流通过导体时，导体的电阻为零",
            "answer": "F",
            "difficuly": 0,
            "part": "尚未完成的功能"
        },
        {
            "question": "横截面积越小的导体，阻值越大",
            "answer": "F",
            "difficuly": 1,
            "part": "尚未完成的功能"
        },
        {
            "question": "电阻是导体对电流的阻碍作用，所以电阻越大电流一定越小",
            "answer": "F",
            "difficuly": 1,
            "part": "尚未完成的功能"
        },
        {
            "question": "通过电阻的电流越小，电阻阻值越大",
            "answer": "F",
            "difficuly": 1,
            "part": "尚未完成的功能"
        },
        {
            "question": "某一定值电阻两端电压越大，通过电阻的电流越大",
            "answer": "T",
            "difficuly": 1,
            "part": "尚未完成的功能"
        },
        {
            "question": "当电阻一定时，导体两端的电压与通过导体的电流成正比",
            "answer": "F",
            "difficuly": 2,
            "part": "尚未完成的功能"
        },
        {
            "question": "当电阻一定时，通过导体的电流与导体两端的电压成正比",
            "answer": "T",
            "difficuly": 1,
            "part": "尚未完成的功能"
        },
        {
            "question": "当导体两端的电压一定时，导体的电阻与通过导体的电流成反比",
            "answer": "F",
            "difficuly": 2,
            "part": "尚未完成的功能"
        },
        {
            "question": "电压一定时，电路中接入电阻的数量越多，电流越小",
            "answer": "F",
            "difficuly": 2,
            "part": "尚未完成的功能"
        },
        {
            "question": "在电路连接方式保持不变时，只增大一个用电器的电阻，整个电路等效电阻一定增大",
            "answer": "T",
            "difficuly": 3,
            "part": "尚未完成的功能"
        },
        {
            "question": "电路中电流通过用电器做的电功，一定等于电路中消耗的电能",
            "answer": "T",
            "difficuly": 2,
            "part": "尚未完成的功能"
        },
        {
            "question": "电流做功越快，电功率一定越大",
            "answer": "T",
            "difficuly": 1,
            "part": "尚未完成的功能"
        },
        {
            "question": "电功率越大的用电器消耗的电能越多",
            "answer": "F",
            "difficuly": 1,
            "part": "尚未完成的功能"
        },
        {
            "question": "电熨斗、洗衣机都是利用电流热效应工作的",
            "answer": "F",
            "difficuly": 1,
            "part": "尚未完成的功能"
        },
        {
            "question": "标有“880V 60W”的灯泡一定比标有“110V 40W”的灯泡亮",
            "answer": "F",
            "difficuly": 1,
            "part": "尚未完成的功能"
        },
        {
            "question": "电流越大的灯泡，亮度越大",
            "answer": "F",
            "difficuly": 1,
            "part": "尚未完成的功能"
        },
        {
            "question": "电流通过用电器产生的热量，一定等于电流通过用电器所做的功",
            "answer": "F",
            "difficuly": 1,
            "part": "尚未完成的功能"
        },
        {
            "question": "当电阻一定时，通过导体的电流越大，产生的热量越多",
            "answer": "F",
            "difficuly": 1,
            "part": "尚未完成的功能"
        },
        {
            "question": "在家庭电路中，同时工作的用电器越多，干路电流一定越小",
            "answer": "F",
            "difficuly": 1,
            "part": "尚未完成的功能"
        },
        {
            "question": "家庭电路中工作的用电器越多，消耗的电能一定越多",
            "answer": "F",
            "difficuly": 1,
            "part": "尚未完成的功能"
        },
        {
            "question": "家庭电路中的用电器都是并联的",
            "answer": "T",
            "difficuly": 2,
            "part": "尚未完成的功能"
        },
        {
            "question": "家庭电路中新增加一个用电器时，总电阻变大",
            "answer": "F",
            "difficuly": 2,
            "part": "尚未完成的功能"
        },
        {
            "question": "中国家庭照明电路的电压是 220V",
            "answer": "T",
            "difficuly": 0,
            "part": "尚未完成的功能"
        },
        {
            "question": "保险丝熔断可能是电路的总功率过大造成的",
            "answer": "T",
            "difficuly": 0,
            "part": "尚未完成的功能"
        },
        {
            "question": "指南针能指南北是由于地磁场对指南针磁极有力的作用",
            "answer": "T",
            "difficuly": 0,
            "part": "尚未完成的功能"
        },
        {
            "question": "小磁针自由静止时，小磁针的 N 极指向地磁场的 S 极",
            "answer": "T",
            "difficuly": 0,
            "part": "尚未完成的功能"
        },
        {
            "question": "磁体之间的相互作用是通过磁场发生的",
            "answer": "T",
            "difficuly": 0,
            "part": "尚未完成的功能"
        },
        {
            "question": "磁场中某点的磁场方向是由放在该点的小磁针决定的",
            "answer": "F",
            "difficuly": 3,
            "part": "尚未完成的功能"
        },
        {
            "question": "磁感线是真实存在的，磁场由无数条磁感线组成",
            "answer": "F",
            "difficuly": 0,
            "part": "尚未完成的功能"
        },
        {
            "question": "磁场对放入其中的小磁针一定有力的作用",
            "answer": "T",
            "difficuly": 1,
            "part": "尚未完成的功能"
        },
        {
            "question": "磁场中某点，小磁针自由静止时北极所指的方向为该点的磁场方向",
            "answer": "T",
            "difficuly": 1,
            "part": "尚未完成的功能"
        },
        {
            "question": "利用撒在磁体周围的铁屑可以判断该磁体周围各点的磁场方向",
            "answer": "F",
            "difficuly": 3,
            "part": "尚未完成的功能"
        },
        {
            "question": "利用放在磁体周围小磁针自由静止时的指向，可以判断该磁体周围各点的磁场方向",
            "answer": "T",
            "difficuly": 1,
            "part": "尚未完成的功能"
        },
        {
            "question": "奥斯特实验表明通电导体周围存在磁场",
            "answer": "T",
            "difficuly": 1,
            "part": "尚未完成的功能"
        },
        {
            "question": "给通电螺线管通电能够产生磁场",
            "answer": "T",
            "difficuly": 1,
            "part": "尚未完成的功能"
        },
        {
            "question": "金属导体周围存在磁场",
            "answer": "F",
            "difficuly": 1,
            "part": "尚未完成的功能"
        },
        {
            "question": "电磁铁是根据电流的磁效应制成的",
            "answer": "T",
            "difficuly": 1,
            "part": "尚未完成的功能"
        },
        {
            "question": "电磁铁磁性的强弱与电磁铁线圈的匝数有关",
            "answer": "T",
            "difficuly": 1,
            "part": "尚未完成的功能"
        },
        {
            "question": "电磁铁的磁极方向与电流方向有关",
            "answer": "T",
            "difficuly": 1,
            "part": "尚未完成的功能"
        },
        {
            "question": "电磁继电器在电路中的作用相当于一个开关",
            "answer": "T",
            "difficuly": 1,
            "part": "尚未完成的功能"
        },
        {
            "question": "导体中的负电荷在做定向移动时一定产生磁场",
            "answer": "T",
            "difficuly": 1,
            "part": "尚未完成的功能"
        },
        {
            "question": "放在磁场中的导体，一定受到磁场的作用力",
            "answer": "F",
            "difficuly": 1,
            "part": "尚未完成的功能"
        },
        {
            "question": "通电线圈在磁场中受力转动的过程中，机械能转化为电能",
            "answer": "F",
            "difficuly": 1,
            "part": "尚未完成的功能"
        },
        {
            "question": "通电导体在磁场中受力方向和电流方向有关",
            "answer": "T",
            "difficuly": 1,
            "part": "尚未完成的功能"
        },
        {
            "question": "电动机是利用通电导体在磁场中受到力的作用的原理工作的",
            "answer": "T",
            "difficuly": 1,
            "part": "尚未完成的功能"
        },
        {
            "question": "电动机将电能转化成机械能",
            "answer": "T",
            "difficuly": 1,
            "part": "尚未完成的功能"
        },
        {
            "question": "在面包店门前可以闻到烤面包的香味，这是扩散现象",
            "answer": "T",
            "difficuly": 1,
            "part": "尚未完成的功能"
        },
        {
            "question": "花香四溢是因为分子在不断的做无规则运动",
            "answer": "T",
            "difficuly": 1,
            "part": "尚未完成的功能"
        },
        {
            "question": "长时间压在一起的铅板和金板互相渗入，这种现象是扩散现象",
            "answer": "T",
            "difficuly": 1,
            "part": "尚未完成的功能"
        },
        {
            "question": "打扫卫生时房间内尘土飞扬，这种现象说明分子在不停地做无规则运动",
            "answer": "F",
            "difficuly": 1,
            "part": "尚未完成的功能"
        },
        {
            "question": "铁块很难被压缩，是因为分子间存在着斥力",
            "answer": "T",
            "difficuly": 1,
            "part": "尚未完成的功能"
        },
        {
            "question": "压缩弹簧需要力，说明分子间有斥力",
            "answer": "F",
            "difficuly": 1,
            "part": "尚未完成的功能"
        },
        {
            "question": "塑料吸盘能牢牢地吸附在玻璃上，主要是由于分子间存在着引力",
            "answer": "F",
            "difficuly": 1,
            "part": "尚未完成的功能"
        },
        {
            "question": "寒冷的冬天，玻璃窗上出现冰花，属于凝华现象",
            "answer": "T",
            "difficuly": 1,
            "part": "尚未完成的功能"
        },
        {
            "question": "炎热的夏天，雪糕周围出现的“白气”是雪糕冒出的水蒸气液化形成的",
            "answer": "F",
            "difficuly": 1,
            "part": "尚未完成的功能"
        },
        {
            "question": "对正在沸腾的水继续加热，水温将不再上升",
            "answer": "T",
            "difficuly": 1,
            "part": "尚未完成的功能"
        },
        {
            "question": "0℃的冰没有内能，分子不运动",
            "answer": "F",
            "difficuly": 0,
            "part": "尚未完成的功能"
        },
        {
            "question": "一切物体都具有内能",
            "answer": "T",
            "difficuly": 1,
            "part": "尚未完成的功能"
        },
        {
            "question": "晶体熔化时温度不变，则内能也不变",
            "answer": "F",
            "difficuly": 1,
            "part": "尚未完成的功能"
        },
        {
            "question": "晶体放出热量 ，它的内能减小，温度一定降低",
            "answer": "F",
            "difficuly": 1,
            "part": "尚未完成的功能"
        },
        {
            "question": "物体吸收热量，温度可能不变",
            "answer": "T",
            "difficuly": 1,
            "part": "尚未完成的功能"
        },
        {
            "question": "用锯条锯木板时锯条发热，锯条的内能增加，木板的内能减少",
            "answer": "F",
            "difficuly": 1,
            "part": "尚未完成的功能"
        },
        {
            "question": "水壶里的水沸腾时，水蒸气把壶盖顶起，内能转化为机械能",
            "answer": "T",
            "difficuly": 1,
            "part": "尚未完成的功能"
        },
        {
            "question": "物体的温度降低，它可能是放出了热量",
            "answer": "T",
            "difficuly": 1,
            "part": "尚未完成的功能"
        },
        {
            "question": "温度越高的物体，放出的热量越多",
            "answer": "F",
            "difficuly": 1,
            "part": "尚未完成的功能"
        },
        {
            "question": "温度升高越多的物体，吸收的热量越多",
            "answer": "F",
            "difficuly": 1,
            "part": "尚未完成的功能"
        },
        {
            "question": "物体的温度越低，所含的热量越少",
            "answer": "F",
            "difficuly": 1,
            "part": "尚未完成的功能"
        },
        {
            "question": "一杯水的温度升高的越高，吸收的热量越多",
            "answer": "T",
            "difficuly": 1,
            "part": "尚未完成的功能"
        },
        {
            "question": "一桶水的比热容和一杯水的比热容一样大",
            "answer": "T",
            "difficuly": 1,
            "part": "尚未完成的功能"
        },
        {
            "question": "内陆地区比沿海地区昼夜温差大，原因之一是砂石的比热容比水的比热容小",
            "answer": "T",
            "difficuly": 1,
            "part": "尚未完成的功能"
        },
        {
            "question": "用水作为汽车发动机散热器的冷却剂，其原因之一是水的比热容较大",
            "answer": "T",
            "difficuly": 1,
            "part": "尚未完成的功能"
        },
        {
            "question": "在阳光照射下，地面温度高于湖水表面温度是因为水的比热容较大",
            "answer": "T",
            "difficuly": 1,
            "part": "尚未完成的功能"
        },
        {
            "question": "汽油机在做功冲程中，机械能转化为内能",
            "answer": "F",
            "difficuly": 1,
            "part": "尚未完成的功能"
        },
        {
            "question": "小孔成的是倒立的虚像",
            "answer": "F",
            "difficuly": 1,
            "part": "尚未完成的功能"
        },
        {
            "question": "阳光透过树叶缝隙在地面形成的圆形光斑是太阳的像",
            "answer": "T",
            "difficuly": 1,
            "part": "尚未完成的功能"
        },
        {
            "question": "镜面反射和漫反射都遵守光的反射定律",
            "answer": "T",
            "difficuly": 1,
            "part": "尚未完成的功能"
        },
        {
            "question": "光线从空气斜射入水中时，折射角一定小于入射角",
            "answer": "T",
            "difficuly": 1,
            "part": "尚未完成的功能"
        },
        {
            "question": "人看到物体成的虚像时，并没有光线射入眼睛",
            "answer": "F",
            "difficuly": 1,
            "part": "尚未完成的功能"
        },
        {
            "question": "在岸上看到水里的鱼比它的实际位置浅一些",
            "answer": "T",
            "difficuly": 0,
            "part": "尚未完成的功能"
        },
        {
            "question": "经凸透镜所成的像都是倒立的",
            "answer": "F",
            "difficuly": 0,
            "part": "尚未完成的功能"
        },
        {
            "question": "人配戴的凹透镜可以矫正近视眼",
            "answer": "T",
            "difficuly": 0,
            "part": "尚未完成的功能"
        },
        {
            "question": "白光是由多种色光组成的",
            "answer": "T",
            "difficuly": 0,
            "part": "尚未完成的功能"
        },
        {
            "question": "人体的安全电压为36V",
            "answer": "F",
            "difficuly": 1,
            "part": "尚未完成的功能"
        },
        {
            "question": "冰融化成水的过程中，比热容减小",
            "answer": "F",
            "difficuly": 2,
            "part": "尚未完成的功能"
        },
        {
            "question": "人能从不同方向看到同一个物体，主要归功于镜面反射",
            "answer": "F",
            "difficuly": 1,
            "part": "尚未完成的功能"
        },
        {
            "question": "物体的动能与物体质量无关",
            "answer": "F",
            "difficuly": 0,
            "part": "尚未完成的功能"
        },
        {
            "question": "热传递中，热量总是从内能大的物体传递到内能小的物体",
            "answer": "F",
            "difficuly": 2,
            "part": "尚未完成的功能"
        },
        {
            "question": "热传递中，热量总是从温度高的物体传到温度低的物体",
            "answer": "T",
            "difficuly": 2,
            "part": "尚未完成的功能"
        },
        {
            "question": "热水的内能一定比冷水的大",
            "answer": "F",
            "difficuly": 0,
            "part": "尚未完成的功能"
        },
        {
            "question": "电流表的使用规范是：电流从负接线柱进入，从正接线柱流出",
            "answer": "F",
            "difficuly": 0,
            "part": "尚未完成的功能"
        },
        {
            "question": "灯泡的螺旋金属部位一定要接到零线上",
            "answer": "T",
            "difficuly": 1,
            "part": "尚未完成的功能"
        },
        {
            "question": "开关要接到灯泡和火线之间",
            "answer": "T",
            "difficuly": 1,
            "part": "尚未完成的功能"
        },
        {
            "question": "电器的金属外壳一定要接地",
            "answer": "T",
            "difficuly": 1,
            "part": "尚未完成的功能"
        },
        {
            "question": "不接触低压带电体",
            "answer": "T",
            "difficuly": 0,
            "part": "尚未完成的功能"
        },
        {
            "question": "不靠近高压带电体",
            "answer": "T",
            "difficuly": 0,
            "part": "尚未完成的功能"
        },
        {
            "question": "电压表的大量程为0~3V",
            "answer": "F",
            "difficuly": 1,
            "part": "尚未完成的功能"
        },
        {
            "question": "扬声器的工作原理是电流的磁效应",
            "answer": "F",
            "difficuly": 1,
            "part": "尚未完成的功能"
        },
        {
            "question": "洗衣机的工作原理是电流的热效应",
            "answer": "F",
            "difficuly": 1,
            "part": "尚未完成的功能"
        },
        {
            "question": "声的传播速度不受温度的影响",
            "answer": "F",
            "difficuly": 1,
            "part": "尚未完成的功能"
        },
        {
            "question": "光在同种不均匀介质中沿直线传播",
            "answer": "F",
            "difficuly": 1,
            "part": "尚未完成的功能"
        },
        {
            "question": "光的传播速度在任何介质中都是3.0×10的8次方米每秒",
            "answer": "F",
            "difficuly": 2,
            "part": "尚未完成的功能"
        },
        {
            "question": "水的密度为1.0×10的三次方kg/立方米",
            "answer": "T",
            "difficuly": 1,
            "part": "尚未完成的功能"
        },
        {
            "question": "电灯只把电能转化为光能",
            "answer": "F",
            "difficuly": 0,
            "part": "尚未完成的功能"
        },
        {
            "question": "声音不能传递信息",
            "answer": "F",
            "difficuly": 0,
            "part": "尚未完成的功能"
        },
        {
            "question": "反复弯折铁丝，铁丝发烫，内能减小",
            "answer": "F",
            "difficuly": 0,
            "part": "尚未完成的功能"
        },
        {
            "question": "凝固需要吸热",
            "answer": "F",
            "difficuly": 0,
            "part": "尚未完成的功能"
        },
        {
            "question": "早晨雾的形成需要吸热",
            "answer": "F",
            "difficuly": 0,
            "part": "尚未完成的功能"
        },
        {
            "question": "碘升华需要放热",
            "answer": "F",
            "difficuly": 0,
            "part": "尚未完成的功能"
        },
        {
            "question": "麦克风的工作原理是电流的磁效应",
            "answer": "F",
            "difficuly": 1,
            "part": "尚未完成的功能"
        },
        {
            "question": "麦克风的工作原理是电磁感应",
            "answer": "T",
            "difficuly": 1,
            "part": "尚未完成的功能"
        },
        {
            "question": "发电机的工作原理是电磁感应",
            "answer": "T",
            "difficuly": 1,
            "part": "尚未完成的功能"
        },
        {
            "question": "在探究阻力对物体运动的影响实验中，小车在水平面上运动的距离反映了阻力的大小",
            "answer": "F",
            "difficuly": 3,
            "part": "尚未完成的功能"
        },
        {
            "question": "在探究阻力对物体运动的影响实验中，小车在水平面上运动的距离反映了阻力对物体运动的影响，而没有反映阻力的大小",
            "answer": "T",
            "difficuly": 3,
            "part": "尚未完成的功能"
        }
    ]
}